dpkg_validator.py
setup.py
datapkg_validator.egg-info/PKG-INFO
datapkg_validator.egg-info/SOURCES.txt
datapkg_validator.egg-info/dependency_links.txt
datapkg_validator.egg-info/entry_points.txt
datapkg_validator.egg-info/requires.txt
datapkg_validator.egg-info/top_level.txt