Metadata-Version: 1.1
Name: datapkg-validator
Version: 0.1.1
Summary: Validate data packages on the commandline using datapackage-validate
Home-page: http://github.com/rlafuente/datapackage-validator/
Author: Ricardo Lafuente
Author-email: r@manufacturaindependente.org
License: GPL
Download-URL: https://github.com/rlafuente/datapackage-validator/tarball/master
Platform: UNKNOWN
